Lab6_2019CSB1084/FPGA.v
module logic_tile(out,clock,in1,in2,in3,in4,in5);
    input clock;
    input in1;
    input in2,in3,in4,in5;
    wire control;
    output out;
    reg [32:0] mem;
    reg q;
    reg qbar;
    wire d;

    initial begin
      q = 1'b0;
    end

    
    assign control=mem[32];
    assign d=mem[{in5,in4,in3,in2,in1}];
    always@(posedge clock)
        begin
            q <=d;
            qbar=!d;
        end


    assign out=(control & q) | (~control & d);
endmodule
module switch_box_4x4(out,in);
    input [3:0] in;
    reg [15:0] configure;
    output [3:0] out;
    assign out[0]= ((in[0] & configure[0]) | (in[1] & configure[1])) | ((in[2] & configure[2]) | (in[3] & configure[3]));
    assign out[1]= ((in[0] & configure[4]) | (in[1] & configure[5])) | ((in[2] & configure[6]) | (in[3] & configure[7]));
    assign out[2]= ((in[0] & configure[8]) | (in[1] & configure[9])) | ((in[2] & configure[10]) | (in[3] & configure[11]));
    assign out[3]= ((in[0] & configure[12]) | (in[1] & configure[13])) | ((in[2] & configure[14]) | (in[3] & configure[15]));
endmodule
module universal_shift_register(data_load,control,clock,out_final,serial_input,c2);

    input c2;

    input [1:0] control;
    input serial_input;
    input clock;
    input [7:0] data_load;
    output [7:0] out_final;
    wire [7:0] out1,out2;
    wire [7:0] temp_output;

    wire [3:0] temp,temp1,temp2,temp3,temp4,temp5,temp6,temp7,temp8,temp9,temp10,temp11,temp12,temp13,temp14,temp15,temp16;

    switch_box_4x4 inst1(.out(temp),.in({1'b0,1'b0,1'b0,c2}));//in decoder c2 will be selected and in universal it will be 0
    switch_box_4x4 inst2(.out(temp1),.in({data_load[0],out2[0],out1[0],control[0]}));//in decoder {0,0,control0,control0} and in unviversal {0,0,out1,out2}
    switch_box_4x4 inst3(.out(temp2),.in({data_load[1],out2[1],out1[1],control[0]}));
    switch_box_4x4 inst4(.out(temp3),.in({data_load[2],out2[2],out1[2],control[0]}));
    switch_box_4x4 inst5(.out(temp4),.in({data_load[3],out2[3],out1[3],control[0]}));
    switch_box_4x4 inst6(.out(temp5),.in({data_load[0],out2[4],out1[4],control[0]}));
    switch_box_4x4 inst7(.out(temp6),.in({data_load[1],out2[5],out1[5],control[0]}));
    switch_box_4x4 inst8(.out(temp7),.in({data_load[2],out2[6],out1[6],control[0]}));
    switch_box_4x4 inst9(.out(temp8),.in({data_load[3],out2[7],out1[7],control[0]}));
    switch_box_4x4 inst10(.out(temp9),.in({data_load[4],control[1],1'b0,1'b0}));
    switch_box_4x4 inst11(.out(temp10),.in({data_load[5],control[1],1'b0,1'b0}));
    switch_box_4x4 inst12(.out(temp11),.in({data_load[6],control[1],1'b0,1'b0}));
    switch_box_4x4 inst13(.out(temp12),.in({data_load[7],control[1],1'b0,1'b0}));
    switch_box_4x4 inst14(.out(temp13),.in({c2,1'b0,1'b0,1'b0}));
    switch_box_4x4 inst15(.out(temp14),.in({out_final[0],1'b0,1'b0,1'b0}));
    switch_box_4x4 inst16(.out(temp15),.in({out_final[1],1'b0,1'b0,1'b0}));
    switch_box_4x4 inst17(.out(temp16),.in({out_final[2],1'b0,1'b0,1'b0}));



    

    logic_tile ins1(.out(out1[0]),.clock(clock),.in1(out_final[1]),.in2(serial_input),.in3(out_final[0]),.in4(data_load[0]),.in5(control[0]));//in decoder out_final will be selected
    logic_tile ins2(.out(out1[1]),.clock(clock),.in1(out_final[2]),.in2(out_final[0]),.in3(out_final[1]),.in4(data_load[1]),.in5(control[0]));
    logic_tile ins3(.out(out1[2]),.clock(clock),.in1(out_final[3]),.in2(out_final[1]),.in3(out_final[2]),.in4(data_load[2]),.in5(control[0]));
    logic_tile ins4(.out(out1[3]),.clock(clock),.in1(out_final[4]),.in2(out_final[2]),.in3(out_final[3]),.in4(data_load[3]),.in5(control[0]));
    logic_tile ins5(.out(out1[4]),.clock(clock),.in1(out_final[5]),.in2(out_final[3]),.in3(out_final[4]),.in4(data_load[4]),.in5(control[0]));
    logic_tile ins6(.out(out1[5]),.clock(clock),.in1(out_final[6]),.in2(out_final[4]),.in3(out_final[5]),.in4(data_load[5]),.in5(control[0]));
    logic_tile ins7(.out(out1[6]),.clock(clock),.in1(out_final[7]),.in2(out_final[5]),.in3(out_final[6]),.in4(data_load[6]),.in5(control[0]));
    logic_tile ins8(.out(out1[7]),.clock(clock),.in1(serial_input),.in2(out_final[6]),.in3(out_final[7]),.in4(data_load[7]),.in5(control[0]));

    logic_tile ins9(.out(out2[0]),.clock(clock),.in1(out_final[1]),.in2(serial_input),.in3(out_final[0]),.in4(data_load[0]),.in5(control[0]));
    logic_tile ins10(.out(out2[1]),.clock(clock),.in1(out_final[2]),.in2(out_final[0]),.in3(out_final[1]),.in4(data_load[1]),.in5(control[0]));
    logic_tile ins11(.out(out2[2]),.clock(clock),.in1(out_final[3]),.in2(out_final[1]),.in3(out_final[2]),.in4(data_load[2]),.in5(control[0]));
    logic_tile ins12(.out(out2[3]),.clock(clock),.in1(out_final[4]),.in2(out_final[2]),.in3(out_final[3]),.in4(data_load[3]),.in5(control[0]));
    logic_tile ins13(.out(out2[4]),.clock(clock),.in1(out_final[5]),.in2(out_final[3]),.in3(out_final[4]),.in4(data_load[4]),.in5(control[0]));
    logic_tile ins14(.out(out2[5]),.clock(clock),.in1(out_final[6]),.in2(out_final[4]),.in3(out_final[5]),.in4(data_load[5]),.in5(control[0]));
    logic_tile ins15(.out(out2[6]),.clock(clock),.in1(out_final[7]),.in2(out_final[5]),.in3(out_final[6]),.in4(data_load[6]),.in5(control[0]));
    logic_tile ins16(.out(out2[7]),.clock(clock),.in1(serial_input),.in2(out_final[6]),.in3(out_final[7]),.in4(data_load[7]),.in5(control[0]));

    logic_tile ins17(.out(out_final[0]),.clock(clock),.in1(temp1[0]),.in2(temp1[1]),.in3(temp9[0]),.in4(temp[0]),.in5(temp13[0]));//temp1[0] contains num1 bit temp9[0] num2 bit and temp13[0] contains carry bit
    logic_tile ins18(.out(out_final[1]),.clock(clock),.in1(temp2[0]),.in2(temp2[1]),.in3(temp10[0]),.in4(temp[0]),.in5(temp14[0]));
    logic_tile ins19(.out(out_final[2]),.clock(clock),.in1(temp3[0]),.in2(temp3[1]),.in3(temp11[0]),.in4(temp[0]),.in5(temp15[0]));
    logic_tile ins20(.out(out_final[3]),.clock(clock),.in1(temp4[0]),.in2(temp4[1]),.in3(temp12[0]),.in4(temp[0]),.in5(temp16[0]));
    logic_tile ins21(.out(out_final[4]),.clock(clock),.in1(temp5[0]),.in2(temp5[1]),.in3(temp9[0]),.in4(temp[0]),.in5(temp13[0]));//temp13[0] contains cin bit
    logic_tile ins22(.out(out_final[5]),.clock(clock),.in1(temp6[0]),.in2(temp6[1]),.in3(temp10[0]),.in4(temp[0]),.in5(temp14[0]));
    logic_tile ins23(.out(out_final[6]),.clock(clock),.in1(temp7[0]),.in2(temp7[1]),.in3(temp11[0]),.in4(temp[0]),.in5(temp15[0]));
    logic_tile ins24(.out(out_final[7]),.clock(clock),.in1(temp8[0]),.in2(temp8[1]),.in3(temp12[0]),.in4(temp[0]),.in5(temp16[0]));
endmodule

Lab6_2019CSB1084/lab6_testbench3.v
module test_bench();
  reg [31:0] tb_mem [0:15];
  reg [1:0] control_tb;//11 => data load; 00 => right shift; 01 => left shift; 10 => retain;
  reg clk;
  initial clk = 0;
  always 
    begin
      #10 clk = ~clk;
    end
  reg serial_input_tb;//0=>parallel input; 1=>serial input;
  reg [7:0] data_load_tb;
  wire [7:0] lab6_output;
  reg c2_tb;
  universal_shift_register ins(.data_load(data_load_tb),.control(control_tb),.clock(clk),.out_final(lab6_output),.serial_input(serial_input_tb),.c2(c2_tb));
  initial 
    begin 
      
      $readmemh("lab6_configure3.mem",tb_mem);
      ins.inst1.configure = tb_mem[13];//0000
      ins.inst2.configure = tb_mem[14];//0024 {00,in2,int3};
      ins.inst3.configure = tb_mem[14];
      ins.inst4.configure = tb_mem[14];
      ins.inst5.configure = tb_mem[14];
      ins.inst6.configure = tb_mem[14];
      ins.inst7.configure = tb_mem[14];
      ins.inst8.configure = tb_mem[14];
      ins.inst9.configure = tb_mem[14];
      ins.inst10.configure = tb_mem[15];//0004
      ins.inst11.configure = tb_mem[15];
      ins.inst12.configure = tb_mem[15];
      ins.inst13.configure = tb_mem[15];
      ins.inst14.configure = tb_mem[14];
      ins.inst15.configure = tb_mem[14];
      ins.inst16.configure = tb_mem[14];
      ins.inst17.configure = tb_mem[14];

      ins.ins1.mem = {1'b0, tb_mem[0]};//CCCCAAAA
      ins.ins2.mem = {1'b0, tb_mem[0]};
      ins.ins3.mem = {1'b0, tb_mem[0]};
      ins.ins4.mem = {1'b0, tb_mem[0]};
      ins.ins5.mem = {1'b0, tb_mem[0]};
      ins.ins6.mem = {1'b0, tb_mem[0]};
      ins.ins7.mem = {1'b0, tb_mem[0]};
      ins.ins8.mem = {1'b0, tb_mem[0]};

      ins.ins9.mem =  {1'b0, tb_mem[1]};//FF00F0F0
      ins.ins10.mem = {1'b0, tb_mem[1]};
      ins.ins11.mem = {1'b0, tb_mem[1]};
      ins.ins12.mem = {1'b0, tb_mem[1]};
      ins.ins13.mem = {1'b0, tb_mem[1]};
      ins.ins14.mem = {1'b0, tb_mem[1]};
      ins.ins15.mem = {1'b0, tb_mem[1]};
      ins.ins16.mem = {1'b0, tb_mem[1]};

      
      ins.ins17.mem = {1'b1, tb_mem[2]};//000000AC 
      ins.ins18.mem = {1'b1, tb_mem[2]}; 
      ins.ins19.mem = {1'b1, tb_mem[2]}; 
      ins.ins20.mem = {1'b1, tb_mem[2]}; 
      ins.ins21.mem = {1'b1, tb_mem[2]}; 
      ins.ins22.mem = {1'b1, tb_mem[2]}; 
      ins.ins23.mem = {1'b1, tb_mem[2]}; 
      ins.ins24.mem = {1'b1, tb_mem[2]}; 
      c2_tb=1'b0;


      data_load_tb    = 8'b10101100;
      control_tb      = 2'b11;//load_data;
      serial_input_tb = 1'b0;
      #20 $display("Output is : %b",lab6_output);

      data_load_tb    = 8'b11001001;
      control_tb      = 2'b10;//retain;
      serial_input_tb = 1'b0;
      #20 $display("Output is : %b",lab6_output);

      data_load_tb    = 8'b11001001;
      control_tb      = 2'b11;//load_data;
      serial_input_tb = 1'b0;
      #20 $display("Output is : %b",lab6_output);

      data_load_tb    = 8'b11001001;
      control_tb      = 2'b00;//right shift;
      serial_input_tb = 1'b0;
      #20 $display("Output is : %b",lab6_output);
      $display("Serial output right is %b",lab6_output[0]);

      data_load_tb    = 8'b11001001;
      control_tb      = 2'b10;//retain;
      serial_input_tb = 1'b0;
      #20 $display("Output is : %b",lab6_output);

      data_load_tb    = 8'b11001001;
      control_tb      = 2'b01;//left shift;
      serial_input_tb = 1'b0;
      #20 $display("Output is : %b",lab6_output);
      $display("Serial output left is %b",lab6_output[7]);

      data_load_tb    = 8'b11001001;
      control_tb      = 2'b00;//right shift;
      serial_input_tb = 1'b1;
      #20 $display("Output is : %b",lab6_output);
      $display("Serial output right is %b",lab6_output[0]);

      data_load_tb    = 8'b11001001;
      control_tb      = 2'b01;//left shift;
      serial_input_tb = 1'b1;
      #20 $display("Output is : %b",lab6_output);
      $display("Serial output left is %b",lab6_output[7]);

      data_load_tb    = 8'b11110000;
      control_tb      = 2'b11;//load_data;
      serial_input_tb = 1'b0;
      #20 $display("Output is : %b",lab6_output);


      data_load_tb    = 8'b11001001;
      control_tb      = 2'b01;//left shift;
      serial_input_tb = 1'b0;
      #20 $display("Output is : %b",lab6_output);
      $display("Serial output left is %b",lab6_output[7]);

      data_load_tb    = 8'b11001001;
      control_tb      = 2'b10;//retain;
      serial_input_tb = 1'b0;
      #20 $display("Output is : %b",lab6_output);
      
      
    end
  
  initial 
      #250 $finish;
 
  initial
    begin
      $dumpfile("ha3.vcd");
      $dumpvars;      
    end
  
endmodule

Lab6_2019CSB1084/ha2.vcd
$date
	Tue Nov 24 05:29:12 2020
$end
$version
	Icarus Verilog
$end
$timescale
	1s
$end
$scope module test_bench $end
$var wire 8 ! lab6_output [7:0] $end
$var reg 1 " c2_tb $end
$var reg 1 # clk $end
$var reg 2 $ control_tb [1:0] $end
$var reg 8 % data_load_tb [7:0] $end
$var reg 1 & serial_input_tb $end
$scope module ins $end
$var wire 1 " c2 $end
$var wire 1 # clock $end
$var wire 2 ' control [1:0] $end
$var wire 8 ( data_load [7:0] $end
$var wire 1 & serial_input $end
$var wire 4 ) temp9 [3:0] $end
$var wire 4 * temp8 [3:0] $end
$var wire 4 + temp7 [3:0] $end
$var wire 4 , temp6 [3:0] $end
$var wire 4 - temp5 [3:0] $end
$var wire 4 . temp4 [3:0] $end
$var wire 4 / temp3 [3:0] $end
$var wire 4 0 temp2 [3:0] $end
$var wire 4 1 temp16 [3:0] $end
$var wire 4 2 temp15 [3:0] $end
$var wire 4 3 temp14 [3:0] $end
$var wire 4 4 temp13 [3:0] $end
$var wire 4 5 temp12 [3:0] $end
$var wire 4 6 temp11 [3:0] $end
$var wire 4 7 temp10 [3:0] $end
$var wire 4 8 temp1 [3:0] $end
$var wire 4 9 temp [3:0] $end
$var wire 8 : out_final [7:0] $end
$var wire 8 ; out2 [7:0] $end
$var wire 8 < out1 [7:0] $end
$scope module ins1 $end
$var wire 1 # clock $end
$var wire 1 = in1 $end
$var wire 1 & in2 $end
$var wire 1 > in3 $end
$var wire 1 ? in4 $end
$var wire 1 @ in5 $end
$var wire 1 A out $end
$var wire 1 B d $end
$var wire 1 C control $end
$var reg 33 D mem [32:0] $end
$var reg 1 E q $end
$var reg 1 F qbar $end
$upscope $end
$scope module ins10 $end
$var wire 1 # clock $end
$var wire 1 G in1 $end
$var wire 1 H in2 $end
$var wire 1 I in3 $end
$var wire 1 J in4 $end
$var wire 1 K in5 $end
$var wire 1 L out $end
$var wire 1 M d $end
$var wire 1 N control $end
$var reg 33 O mem [32:0] $end
$var reg 1 P q $end
$var reg 1 Q qbar $end
$upscope $end
$scope module ins11 $end
$var wire 1 # clock $end
$var wire 1 R in1 $end
$var wire 1 S in2 $end
$var wire 1 T in3 $end
$var wire 1 U in4 $end
$var wire 1 V in5 $end
$var wire 1 W out $end
$var wire 1 X d $end
$var wire 1 Y control $end
$var reg 33 Z mem [32:0] $end
$var reg 1 [ q $end
$var reg 1 \ qbar $end
$upscope $end
$scope module ins12 $end
$var wire 1 # clock $end
$var wire 1 ] in1 $end
$var wire 1 ^ in2 $end
$var wire 1 _ in3 $end
$var wire 1 ` in4 $end
$var wire 1 a in5 $end
$var wire 1 b out $end
$var wire 1 c d $end
$var wire 1 d control $end
$var reg 33 e mem [32:0] $end
$var reg 1 f q $end
$var reg 1 g qbar $end
$upscope $end
$scope module ins13 $end
$var wire 1 # clock $end
$var wire 1 h in1 $end
$var wire 1 i in2 $end
$var wire 1 j in3 $end
$var wire 1 k in4 $end
$var wire 1 l in5 $end
$var wire 1 m out $end
$var wire 1 n d $end
$var wire 1 o control $end
$var reg 33 p mem [32:0] $end
$var reg 1 q q $end
$var reg 1 r qbar $end
$upscope $end
$scope module ins14 $end
$var wire 1 # clock $end
$var wire 1 s in1 $end
$var wire 1 t in2 $end
$var wire 1 u in3 $end
$var wire 1 v in4 $end
$var wire 1 w in5 $end
$var wire 1 x out $end
$var wire 1 y d $end
$var wire 1 z control $end
$var reg 33 { mem [32:0] $end
$var reg 1 | q $end
$var reg 1 } qbar $end
$upscope $end
$scope module ins15 $end
$var wire 1 # clock $end
$var wire 1 ~ in1 $end
$var wire 1 !" in2 $end
$var wire 1 "" in3 $end
$var wire 1 #" in4 $end
$var wire 1 $" in5 $end
$var wire 1 %" out $end
$var wire 1 &" d $end
$var wire 1 '" control $end
$var reg 33 (" mem [32:0] $end
$var reg 1 )" q $end
$var reg 1 *" qbar $end
$upscope $end
$scope module ins16 $end
$var wire 1 # clock $end
$var wire 1 & in1 $end
$var wire 1 +" in2 $end
$var wire 1 ," in3 $end
$var wire 1 -" in4 $end
$var wire 1 ." in5 $end
$var wire 1 /" out $end
$var wire 1 0" d $end
$var wire 1 1" control $end
$var reg 33 2" mem [32:0] $end
$var reg 1 3" q $end
$var reg 1 4" qbar $end
$upscope $end
$scope module ins17 $end
$var wire 1 # clock $end
$var wire 1 5" in1 $end
$var wire 1 6" in2 $end
$var wire 1 7" in3 $end
$var wire 1 8" in4 $end
$var wire 1 9" in5 $end
$var wire 1 :" out $end
$var wire 1 ;" d $end
$var wire 1 <" control $end
$var reg 33 =" mem [32:0] $end
$var reg 1 >" q $end
$var reg 1 ?" qbar $end
$upscope $end
$scope module ins18 $end
$var wire 1 # clock $end
$var wire 1 @" in1 $end
$var wire 1 A" in2 $end
$var wire 1 B" in3 $end
$var wire 1 C" in4 $end
$var wire 1 D" in5 $end
$var wire 1 E" out $end
$var wire 1 F" d $end
$var wire 1 G" control $end
$var reg 33 H" mem [32:0] $end
$var reg 1 I" q $end
$var reg 1 J" qbar $end
$upscope $end
$scope module ins19 $end
$var wire 1 # clock $end
$var wire 1 K" in1 $end
$var wire 1 L" in2 $end
$var wire 1 M" in3 $end
$var wire 1 N" in4 $end
$var wire 1 O" in5 $end
$var wire 1 P" out $end
$var wire 1 Q" d $end
$var wire 1 R" control $end
$var reg 33 S" mem [32:0] $end
$var reg 1 T" q $end
$var reg 1 U" qbar $end
$upscope $end
$scope module ins2 $end
$var wire 1 # clock $end
$var wire 1 V" in1 $end
$var wire 1 W" in2 $end
$var wire 1 X" in3 $end
$var wire 1 Y" in4 $end
$var wire 1 Z" in5 $end
$var wire 1 [" out $end
$var wire 1 \" d $end
$var wire 1 ]" control $end
$var reg 33 ^" mem [32:0] $end
$var reg 1 _" q $end
$var reg 1 `" qbar $end
$upscope $end
$scope module ins20 $end
$var wire 1 # clock $end
$var wire 1 a" in1 $end
$var wire 1 b" in2 $end
$var wire 1 c" in3 $end
$var wire 1 d" in4 $end
$var wire 1 e" in5 $end
$var wire 1 f" out $end
$var wire 1 g" d $end
$var wire 1 h" control $end
$var reg 33 i" mem [32:0] $end
$var reg 1 j" q $end
$var reg 1 k" qbar $end
$upscope $end
$scope module ins21 $end
$var wire 1 # clock $end
$var wire 1 l" in1 $end
$var wire 1 m" in2 $end
$var wire 1 n" in3 $end
$var wire 1 o" in4 $end
$var wire 1 p" in5 $end
$var wire 1 q" out $end
$var wire 1 r" d $end
$var wire 1 s" control $end
$var reg 33 t" mem [32:0] $end
$var reg 1 u" q $end
$var reg 1 v" qbar $end
$upscope $end
$scope module ins22 $end
$var wire 1 # clock $end
$var wire 1 w" in1 $end
$var wire 1 x" in2 $end
$var wire 1 y" in3 $end
$var wire 1 z" in4 $end
$var wire 1 {" in5 $end
$var wire 1 |" out $end
$var wire 1 }" d $end
$var wire 1 ~" control $end
$var reg 33 !# mem [32:0] $end
$var reg 1 "# q $end
$var reg 1 ## qbar $end
$upscope $end
$scope module ins23 $end
$var wire 1 # clock $end
$var wire 1 $# in1 $end
$var wire 1 %# in2 $end
$var wire 1 &# in3 $end
$var wire 1 '# in4 $end
$var wire 1 (# in5 $end
$var wire 1 )# out $end
$var wire 1 *# d $end
$var wire 1 +# control $end
$var reg 33 ,# mem [32:0] $end
$var reg 1 -# q $end
$var reg 1 .# qbar $end
$upscope $end
$scope module ins24 $end
$var wire 1 # clock $end
$var wire 1 /# in1 $end
$var wire 1 0# in2 $end
$var wire 1 1# in3 $end
$var wire 1 2# in4 $end
$var wire 1 3# in5 $end
$var wire 1 4# out $end
$var wire 1 5# d $end
$var wire 1 6# control $end
$var reg 33 7# mem [32:0] $end
$var reg 1 8# q $end
$var reg 1 9# qbar $end
$upscope $end
$scope module ins3 $end
$var wire 1 # clock $end
$var wire 1 :# in1 $end
$var wire 1 ;# in2 $end
$var wire 1 <# in3 $end
$var wire 1 =# in4 $end
$var wire 1 ># in5 $end
$var wire 1 ?# out $end
$var wire 1 @# d $end
$var wire 1 A# control $end
$var reg 33 B# mem [32:0] $end
$var reg 1 C# q $end
$var reg 1 D# qbar $end
$upscope $end
$scope module ins4 $end
$var wire 1 # clock $end
$var wire 1 E# in1 $end
$var wire 1 F# in2 $end
$var wire 1 G# in3 $end
$var wire 1 H# in4 $end
$var wire 1 I# in5 $end
$var wire 1 J# out $end
$var wire 1 K# d $end
$var wire 1 L# control $end
$var reg 33 M# mem [32:0] $end
$var reg 1 N# q $end
$var reg 1 O# qbar $end
$upscope $end
$scope module ins5 $end
$var wire 1 # clock $end
$var wire 1 P# in1 $end
$var wire 1 Q# in2 $end
$var wire 1 R# in3 $end
$var wire 1 S# in4 $end
$var wire 1 T# in5 $end
$var wire 1 U# out $end
$var wire 1 V# d $end
$var wire 1 W# control $end
$var reg 33 X# mem [32:0] $end
$var reg 1 Y# q $end
$var reg 1 Z# qbar $end
$upscope $end
$scope module ins6 $end
$var wire 1 # clock $end
$var wire 1 [# in1 $end
$var wire 1 \# in2 $end
$var wire 1 ]# in3 $end
$var wire 1 ^# in4 $end
$var wire 1 _# in5 $end
$var wire 1 `# out $end
$var wire 1 a# d $end
$var wire 1 b# control $end
$var reg 33 c# mem [32:0] $end
$var reg 1 d# q $end
$var reg 1 e# qbar $end
$upscope $end
$scope module ins7 $end
$var wire 1 # clock $end
$var wire 1 f# in1 $end
$var wire 1 g# in2 $end
$var wire 1 h# in3 $end
$var wire 1 i# in4 $end
$var wire 1 j# in5 $end
$var wire 1 k# out $end
$var wire 1 l# d $end
$var wire 1 m# control $end
$var reg 33 n# mem [32:0] $end
$var reg 1 o# q $end
$var reg 1 p# qbar $end
$upscope $end
$scope module ins8 $end
$var wire 1 # clock $end
$var wire 1 & in1 $end
$var wire 1 q# in2 $end
$var wire 1 r# in3 $end
$var wire 1 s# in4 $end
$var wire 1 t# in5 $end
$var wire 1 u# out $end
$var wire 1 v# d $end
$var wire 1 w# control $end
$var reg 33 x# mem [32:0] $end
$var reg 1 y# q $end
$var reg 1 z# qbar $end
$upscope $end
$scope module ins9 $end
$var wire 1 # clock $end
$var wire 1 {# in1 $end
$var wire 1 & in2 $end
$var wire 1 |# in3 $end
$var wire 1 }# in4 $end
$var wire 1 ~# in5 $end
$var wire 1 !$ out $end
$var wire 1 "$ d $end
$var wire 1 #$ control $end
$var reg 33 $$ mem [32:0] $end
$var reg 1 %$ q $end
$var reg 1 &$ qbar $end
$upscope $end
$scope module inst1 $end
$var wire 4 '$ in [3:0] $end
$var wire 4 ($ out [3:0] $end
$var reg 16 )$ configure [15:0] $end
$upscope $end
$scope module inst10 $end
$var wire 4 *$ in [3:0] $end
$var wire 4 +$ out [3:0] $end
$var reg 16 ,$ configure [15:0] $end
$upscope $end
$scope module inst11 $end
$var wire 4 -$ in [3:0] $end
$var wire 4 .$ out [3:0] $end
$var reg 16 /$ configure [15:0] $end
$upscope $end
$scope module inst12 $end
$var wire 4 0$ in [3:0] $end
$var wire 4 1$ out [3:0] $end
$var reg 16 2$ configure [15:0] $end
$upscope $end
$scope module inst13 $end
$var wire 4 3$ in [3:0] $end
$var wire 4 4$ out [3:0] $end
$var reg 16 5$ configure [15:0] $end
$upscope $end
$scope module inst14 $end
$var wire 4 6$ in [3:0] $end
$var wire 4 7$ out [3:0] $end
$var reg 16 8$ configure [15:0] $end
$upscope $end
$scope module inst15 $end
$var wire 4 9$ in [3:0] $end
$var wire 4 :$ out [3:0] $end
$var reg 16 ;$ configure [15:0] $end
$upscope $end
$scope module inst16 $end
$var wire 4 <$ in [3:0] $end
$var wire 4 =$ out [3:0] $end
$var reg 16 >$ configure [15:0] $end
$upscope $end
$scope module inst17 $end
$var wire 4 ?$ in [3:0] $end
$var wire 4 @$ out [3:0] $end
$var reg 16 A$ configure [15:0] $end
$upscope $end
$scope module inst2 $end
$var wire 4 B$ in [3:0] $end
$var wire 4 C$ out [3:0] $end
$var reg 16 D$ configure [15:0] $end
$upscope $end
$scope module inst3 $end
$var wire 4 E$ in [3:0] $end
$var wire 4 F$ out [3:0] $end
$var reg 16 G$ configure [15:0] $end
$upscope $end
$scope module inst4 $end
$var wire 4 H$ in [3:0] $end
$var wire 4 I$ out [3:0] $end
$var reg 16 J$ configure [15:0] $end
$upscope $end
$scope module inst5 $end
$var wire 4 K$ in [3:0] $end
$var wire 4 L$ out [3:0] $end
$var reg 16 M$ configure [15:0] $end
$upscope $end
$scope module inst6 $end
$var wire 4 N$ in [3:0] $end
$var wire 4 O$ out [3:0] $end
$var reg 16 P$ configure [15:0] $end
$upscope $end
$scope module inst7 $end
$var wire 4 Q$ in [3:0] $end
$var wire 4 R$ out [3:0] $end
$var reg 16 S$ configure [15:0] $end
$upscope $end
$scope module inst8 $end
$var wire 4 T$ in [3:0] $end
$var wire 4 U$ out [3:0] $end
$var reg 16 V$ configure [15:0] $end
$upscope $end
$scope module inst9 $end
$var wire 4 W$ in [3:0] $end
$var wire 4 X$ out [3:0] $end
$var reg 16 Y$ configure [15:0] $end
$upscope $end
$upscope $end
$upscope $end
$enddefinitions $end
#0
$dumpvars
b10001 Y$
b11 X$
b1001 W$
b10001 V$
b11 U$
b1001 T$
b10001 S$
b11 R$
b1 Q$
b10001 P$
b11 O$
b1 N$
b10001 M$
b11 L$
b1001 K$
b10001 J$
b11 I$
b1001 H$
b10001 G$
b11 F$
b1 E$
b10001 D$
b11 C$
b1 B$
b0 A$
b0 @$
b0 ?$
b0 >$
b0 =$
b0 <$
b0 ;$
b0 :$
b0 9$
b0 8$
b0 7$
b1000 6$
b100 5$
b1 4$
b1100 3$
b100 2$
b1 1$
b100 0$
b100 /$
b1 .$
b1100 -$
b100 ,$
b1 +$
b100 *$
b1 )$
b1 ($
b1 '$
x&$
0%$
b1000 $$
0#$
0"$
0!$
1~#
0}#
0|#
0{#
xz#
0y#
b1 x#
0w#
0v#
0u#
1t#
1s#
1r#
0q#
xp#
0o#
b1 n#
0m#
0l#
0k#
1j#
0i#
0h#
0g#
1f#
xe#
0d#
b1 c#
0b#
0a#
0`#
1_#
1^#
0]#
0\#
0[#
xZ#
0Y#
b1 X#
0W#
0V#
0U#
1T#
0S#
0R#
0Q#
0P#
xO#
0N#
b1 M#
0L#
0K#
0J#
1I#
1H#
0G#
0F#
0E#
xD#
0C#
b1 B#
0A#
0@#
0?#
1>#
1=#
0<#
0;#
0:#
x9#
08#
b1000000000000000 7#
06#
15#
14#
03#
12#
11#
10#
1/#
x.#
0-#
b1000000000000 ,#
0+#
0*#
0)#
0(#
1'#
1&#
1%#
1$#
x##
0"#
b100000000000 !#
0~"
0}"
0|"
0{"
1z"
1y"
1x"
1w"
xv"
0u"
b100000000 t"
0s"
0r"
0q"
0p"
1o"
1n"
1m"
1l"
xk"
0j"
b10000000 i"
0h"
0g"
0f"
0e"
1d"
1c"
1b"
1a"
x`"
0_"
b1 ^"
0]"
0\"
0["
1Z"
0Y"
0X"
0W"
0V"
xU"
0T"
b10000 S"
0R"
0Q"
0P"
0O"
1N"
1M"
1L"
1K"
xJ"
0I"
b1000 H"
0G"
0F"
0E"
0D"
1C"
1B"
1A"
1@"
x?"
0>"
b1 ="
0<"
0;"
0:"
09"
18"
17"
16"
15"
x4"
03"
b1000 2"
01"
00"
0/"
1."
1-"
1,"
0+"
x*"
0)"
b1000 ("
0'"
0&"
0%"
1$"
0#"
0""
0!"
1~
x}
0|
b1000 {
0z
0y
0x
1w
1v
0u
0t
0s
xr
0q
b1000 p
0o
0n
0m
1l
0k
0j
0i
0h
xg
0f
b1000 e
0d
0c
0b
1a
1`
0_
0^
0]
x\
0[
b1000 Z
0Y
0X
0W
1V
1U
0T
0S
0R
xQ
0P
b1000 O
0N
0M
0L
1K
0J
0I
0H
0G
xF
0E
b1 D
0C
0B
0A
1@
0?
0>
0=
b0 <
b0 ;
b10000000 :
b1 9
b11 8
b1 7
b1 6
b1 5
b0 4
b0 3
b0 2
b0 1
b11 0
b11 /
b11 .
b11 -
b11 ,
b11 +
b11 *
b1 )
b10101100 (
b11 '
0&
b10101100 %
b11 $
0#
1"
b10000000 !
$end
#10
18#
1F
1`"
1D#
1O#
1Z#
1e#
1p#
1z#
1&$
1Q
1\
1g
1r
1}
1*"
14"
1?"
1J"
1U"
1k"
1v"
1##
1.#
09#
1#
#20
0,"
0~
0r#
0f#
1i
1_
1R
1Q#
1G#
1:#
04#
b1000 !
b1000 :
1f"
05#
02#
0'#
0z"
0o"
1g"
0d"
0N"
0C"
08"
b0 9
b0 ($
0#
b0 '$
b0 6$
0"
#30
08#
1j"
19#
0k"
1#
#40
1U#
1+"
1""
1s
1q#
1h#
1[#
0i
0_
0R
1V#
0Q#
0G#
0:#
1)#
b1000000 !
b1000000 :
0f"
05"
06"
0@"
0A"
0K"
0L"
0a"
0b"
0l"
0m"
0w"
0x"
1*#
0$#
0%#
0/#
00#
05#
12#
1'#
1z"
1o"
0g"
1d"
1N"
1C"
18"
b0 8
b0 C$
b0 0
b0 F$
b0 /
b0 I$
b0 .
b0 L$
b0 -
b0 O$
b0 ,
b0 R$
b0 +
b0 U$
b0 *
b0 X$
b1 9
b1 ($
1A
1["
b10011 <
0k#
b10 B$
b10 E$
b1000 H$
b1000 K$
b10 N$
b0 Q$
b1000 T$
b1000 W$
1B
0@
1\"
0Z"
0>#
0I#
0T#
0_#
0l#
0j#
0t#
0~#
0K
0V
0a
0l
0w
0$"
0."
0#
b1 '$
b1000 6$
1"
b10 $
b10 '
#50
1E
1_"
1Y#
0j"
1-#
0F
0`"
0Z#
1k"
0.#
1#
#60
b1010 T$
b0 E$
1k#
b1010001 <
0["
0+"
0""
0s
0q#
1l#
0h#
0[#
1^
1T
1G
1F#
1<#
0\"
1V"
b1000 ?$
0)#
b100 !
b100 :
1P"
02#
0*#
0'#
0z"
0o"
0d"
1Q"
0N"
0C"
08"
b0 9
b0 ($
0#
b0 '$
b0 6$
0"
#70
0-#
1T"
1o#
0_"
1.#
0U"
0p#
1`"
1#
